odoo/addons/repair_stock_move_restrict_lot/README.rst
odoo/addons/repair_stock_move_restrict_lot/__init__.py
odoo/addons/repair_stock_move_restrict_lot/__manifest__.py
odoo/addons/repair_stock_move_restrict_lot/i18n/repair_stock_move_restrict_lot.pot
odoo/addons/repair_stock_move_restrict_lot/models/__init__.py
odoo/addons/repair_stock_move_restrict_lot/models/repair_order.py
odoo/addons/repair_stock_move_restrict_lot/readme/CONTRIBUTORS.rst
odoo/addons/repair_stock_move_restrict_lot/readme/DESCRIPTION.rst
odoo/addons/repair_stock_move_restrict_lot/static/description/icon.png
odoo/addons/repair_stock_move_restrict_lot/static/description/index.html
odoo/addons/repair_stock_move_restrict_lot/tests/__init__.py
odoo/addons/repair_stock_move_restrict_lot/tests/test_repair_stock_move.py
odoo_addon_repair_stock_move_restrict_lot-15.0.1.0.0.2.dist-info/METADATA
odoo_addon_repair_stock_move_restrict_lot-15.0.1.0.0.2.dist-info/WHEEL
odoo_addon_repair_stock_move_restrict_lot-15.0.1.0.0.2.dist-info/top_level.txt
odoo_addon_repair_stock_move_restrict_lot-15.0.1.0.0.2.dist-info/RECORD
